adder.t.v
// Adder testbench
`timescale 1 ns / 1 ps
`include "adder.v"

module testFullAdder();
    reg a, b, carryin;
    wire sum, carryout;

    //behavioralFullAdder adder (sum, carryout, a, b, carryin);
    structuralFullAdder adder (sum, carryout, AandB, AxorB, wire0, a, b, carryin);

    initial begin
    $dumpfile("adder.vcd");
    $dumpvars();

    $display("A B Cin | Cout S | Expected Output");
    a=0;b=0;carryin=0; #1000 
    $display("%b  %b  %b |   %b  %b | 0  0 ", a, b, carryin, carryout, sum);
    a=0;b=0;carryin=1; #1000 
    $display("%b  %b  %b |   %b  %b | 0  1 ", a, b, carryin, carryout, sum);

    a=0;b=1;carryin=0; #1000 
    $display("%b  %b  %b |   %b  %b | 0  1 ", a, b, carryin, carryout, sum);
    a=0;b=1;carryin=1; #1000 
    $display("%b  %b  %b |   %b  %b | 1  0 ", a, b, carryin, carryout, sum);

    a=1;b=0;carryin=0; #1000 
    $display("%b  %b  %b |   %b  %b | 0  1 ", a, b, carryin, carryout, sum);
    a=1;b=0;carryin=1; #1000 
    $display("%b  %b  %b |   %b  %b | 1  0 ", a, b, carryin, carryout, sum);

    a=1;b=1;carryin=0; #1000 
    $display("%b  %b  %b |   %b  %b | 1  0 ", a, b, carryin, carryout, sum);
    a=1;b=1;carryin=1; #1000 
    $display("%b  %b  %b |   %b  %b | 1  1 ", a, b, carryin, carryout, sum);
    $finish();
    end
endmodule

adder.v
// Adder circuit

module behavioralFullAdder
(
    output sum, 
    output carryout,
    input a, 
    input b, 
    input carryin
);
    // Uses concatenation operator and built-in '+'
    assign {carryout, sum}=a+b+carryin;
endmodule

module structuralFullAdder
(
    output sum, 
    output carryout,
    output AandB, AxorB, wire0,
    input a, 
    input b, 
    input carryin
);
    // define gates with delays
    `define AND and #50
    `define OR or #50
    `define XOR xor #50

    wire AandB, AxorB, wire0;
    `XOR xorgateA(AxorB,a,b);

    `XOR xorgateB(sum,a,b,carryin);

    `AND andgate(AandB,a,b);
    `AND andgate(wire0,carryin,AxorB);

    `OR orgate(carryout, AandB, wire0);
  
endmodule

adder.vcd
$date
	Thu Sep 20 21:49:21 2018
$end
$version
	Icarus Verilog
$end
$timescale
	1ps
$end
$scope module behavioralFullAdder $end
$var wire 1 ! a $end
$var wire 1 " b $end
$var wire 1 # carryin $end
$var wire 1 $ sum $end
$var wire 1 % carryout $end
$upscope $end
$scope module testFullAdder $end
$var wire 1 & wire0 $end
$var wire 1 ' sum $end
$var wire 1 ( carryout $end
$var wire 1 ) AxorB $end
$var wire 1 * AandB $end
$var reg 1 + a $end
$var reg 1 , b $end
$var reg 1 - carryin $end
$scope module adder $end
$var wire 1 * AandB $end
$var wire 1 ) AxorB $end
$var wire 1 + a $end
$var wire 1 , b $end
$var wire 1 - carryin $end
$var wire 1 ( carryout $end
$var wire 1 ' sum $end
$var wire 1 & wire0 $end
$upscope $end
$upscope $end
$enddefinitions $end
#0
$dumpvars
0-
0,
0+
x*
x)
x(
x'
x&
x%
x$
z#
z"
z!
$end
#50000
0&
0*
0'
0)
#100000
0(
#1000000
1-
#1050000
1'
#2000000
0-
1,
#2050000
1)
#3000000
1-
#3050000
0'
1&
#3100000
1(
#4000000
0-
0,
1+
#4050000
0&
1'
#4100000
0(
#5000000
1-
#5050000
0'
1&
#5100000
1(
#6000000
0-
1,
#6050000
0&
0)
1*
#7000000
1-
#7050000
1'
