decoder.t.v
// Decoder testbench
`timescale 1 ns / 1 ps
`include "decoder.v"

module testDecoder (); 
    reg addr0, addr1;
    reg enable;
    wire out0,out1,out2,out3;

    //behavioralDecoder decoder (out0,out1,out2,out3,addr0,addr1,enable);
    structuralDecoder decoder (out0,out1,out2,out3,nadd0,nadd1,addr0,addr1,enable); // Swap after testing

    initial begin
    $dumpfile("decoder.vcd");
    $dumpvars();

    $display("En A0 A1| O0 O1 O2 O3 | Expected Output");
    enable=0;addr0=0;addr1=0; #1000 
    $display("%b  %b  %b |  %b  %b  %b  %b | All false", enable, addr0, addr1, out0, out1, out2, out3);
    enable=0;addr0=1;addr1=0; #1000
    $display("%b  %b  %b |  %b  %b  %b  %b | All false", enable, addr0, addr1, out0, out1, out2, out3);
    enable=0;addr0=0;addr1=1; #1000 
    $display("%b  %b  %b |  %b  %b  %b  %b | All false", enable, addr0, addr1, out0, out1, out2, out3);
    enable=0;addr0=1;addr1=1; #1000 
    $display("%b  %b  %b |  %b  %b  %b  %b | All false", enable, addr0, addr1, out0, out1, out2, out3);
    enable=1;addr0=0;addr1=0; #1000 
    $display("%b  %b  %b |  %b  %b  %b  %b | O0 Only", enable, addr0, addr1, out0, out1, out2, out3);
    enable=1;addr0=1;addr1=0; #1000 
    $display("%b  %b  %b |  %b  %b  %b  %b | O1 Only", enable, addr0, addr1, out0, out1, out2, out3);
    enable=1;addr0=0;addr1=1; #1000 
    $display("%b  %b  %b |  %b  %b  %b  %b | O2 Only", enable, addr0, addr1, out0, out1, out2, out3);
    enable=1;addr0=1;addr1=1; #1000 
    $display("%b  %b  %b |  %b  %b  %b  %b | O3 Only", enable, addr0, addr1, out0, out1, out2, out3);
    $finish();
    end

endmodule

decoder.v
// Decoder circuit

module behavioralDecoder
(
    output out0, out1, out2, out3,
    input address0, address1,
    input enable
);
    // Uses concatenation and shift operators
    assign {out3,out2,out1,out0}=enable<<{address1,address0};
endmodule


module structuralDecoder
(
    output out0, out1, out2, out3, nadd0, nadd1,
    input address0, address1,
    input enable
);
    // define gates with delays
    `define AND and #50
    `define OR or #50
    `define NOT not #50

    wire nadd0;
    wire nadd1;

    `NOT Ainv(nadd0, address0);
    `NOT Binv(nadd1, address1);

    `AND andgateA(out0,nadd0,nadd1,enable);
    `AND andgateB(out1,address0,nadd1,enable);
    `AND andgateC(out2,nadd0,address1,enable);
    `AND andgateD(out3,address0,address1,enable);

endmodule

decoder.vcd
$date
	Thu Sep 20 21:49:23 2018
$end
$version
	Icarus Verilog
$end
$timescale
	1ps
$end
$scope module behavioralDecoder $end
$var wire 1 ! address0 $end
$var wire 1 " address1 $end
$var wire 1 # enable $end
$var wire 1 $ out3 $end
$var wire 1 % out2 $end
$var wire 1 & out1 $end
$var wire 1 ' out0 $end
$upscope $end
$scope module testDecoder $end
$var wire 1 ( out3 $end
$var wire 1 ) out2 $end
$var wire 1 * out1 $end
$var wire 1 + out0 $end
$var wire 1 , nadd1 $end
$var wire 1 - nadd0 $end
$var reg 1 . addr0 $end
$var reg 1 / addr1 $end
$var reg 1 0 enable $end
$scope module decoder $end
$var wire 1 . address0 $end
$var wire 1 / address1 $end
$var wire 1 0 enable $end
$var wire 1 - nadd0 $end
$var wire 1 , nadd1 $end
$var wire 1 + out0 $end
$var wire 1 * out1 $end
$var wire 1 ) out2 $end
$var wire 1 ( out3 $end
$upscope $end
$upscope $end
$enddefinitions $end
#0
$dumpvars
00
0/
0.
x-
x,
x+
x*
x)
x(
x'
x&
x%
x$
z#
z"
z!
$end
#50000
1,
1-
0(
0)
0*
0+
#1000000
1.
#1050000
0-
#2000000
1/
0.
#2050000
0,
1-
#3000000
1.
#3050000
0-
#4000000
0/
0.
10
#4050000
1,
1-
#4100000
1+
#5000000
1.
#5050000
0-
1*
#5100000
0+
#6000000
1/
0.
#6050000
0,
1-
0*
#6100000
1)
#7000000
1.
#7050000
0-
1(
#7100000
0)
